session_info2/__init__.py
session_info2/__main__.py
session_info2/_dists.py
session_info2/_pu.py
session_info2/_repr.py
session_info2/_ttl_cache.py
session_info2/_widget.py
session_info2/py.typed
session_info2-0.2.2.dist-info/METADATA
session_info2-0.2.2.dist-info/WHEEL
session_info2-0.2.2.dist-info/licenses/LICENSE.rst
session_info2-0.2.2.dist-info/RECORD
